{
  "$schema": "https://playground.wordpress.net/blueprint-schema.json",
  "landingPage": "/wp-admin/post-new.php?post_type=page",
  "preferredVersions": {
    "php": "8.0",
    "wp": "6.8"
  },
  "phpExtensionBundles": [
    "kitchen-sink"
  ],
  "features": {
    "networking": true
  },
  "steps": [
    {
      "step": "login",
      "username": "admin",
      "password": "password"
    },
    {
      "step": "installPlugin",
      "pluginZipFile": {
        "resource": "wordpress.org/plugins",
        "slug": "designsetgo"
      },
      "options": {
        "activate": true
      }
    }
  ]
}
